[
    {
        "time": "09 Nov 2020, 4:02:31 pm",
        "prod_name": "Ноутбук",
        "action": "change"
    },
    {
        "time": "09 Nov 2020, 4:02:31 pm",
        "prod_name": "Ноутбук",
        "action": "remove"
    },
    {
        "time": "09 Nov 2020, 4:02:32 pm",
        "prod_name": "Ноутбук",
        "action": "add"
    },
    {
        "time": "09 Nov 2020, 4:06:11 pm",
        "prod_name": "Keyboard",
        "action": "change"
    },
    {
        "time": "09 Nov 2020, 4:06:13 pm",
        "prod_name": "Gamepad",
        "action": "change"
    },
    {
        "time": "09 Nov 2020, 4:06:15 pm",
        "prod_name": "Ноутбук",
        "action": "change"
    },
    {
        "time": "09 Nov 2020, 4:06:19 pm",
        "prod_name": "Gamepad",
        "action": "change"
    },
    {
        "time": "09 Nov 2020, 4:06:19 pm",
        "prod_name": "Gamepad",
        "action": "remove"
    },
    {
        "time": "09 Nov 2020, 4:06:19 pm",
        "prod_name": "Keyboard",
        "action": "change"
    },
    {
        "time": "09 Nov 2020, 4:06:19 pm",
        "prod_name": "Keyboard",
        "action": "remove"
    },
    {
        "time": "09 Nov 2020, 4:06:20 pm",
        "prod_name": "Ноутбук",
        "action": "change"
    },
    {
        "time": "09 Nov 2020, 4:06:20 pm",
        "prod_name": "Ноутбук",
        "action": "remove"
    },
    {
        "time": "09 Nov 2020, 4:29:53 pm",
        "prod_name": "Мышка",
        "action": "add"
    },
    {
        "time": "09 Nov 2020, 4:29:53 pm",
        "prod_name": "Ноутбук",
        "action": "add"
    },
    {
        "time": "09 Nov 2020, 4:29:54 pm",
        "prod_name": "Gamepad",
        "action": "add"
    },
    {
        "time": "09 Nov 2020, 4:29:55 pm",
        "prod_name": "Keyboard",
        "action": "add"
    },
    {
        "time": "09 Nov 2020, 4:29:57 pm",
        "prod_name": "Ноутбук",
        "action": "remove"
    },
    {
        "time": "09 Nov 2020, 4:29:57 pm",
        "prod_name": "Gamepad",
        "action": "remove"
    },
    {
        "time": "09 Nov 2020, 4:29:58 pm",
        "prod_name": "Keyboard",
        "action": "remove"
    },
    {
        "time": "09 Nov 2020, 4:30:00 pm",
        "prod_name": "Мышка",
        "action": "remove"
    },
    {
        "time": "09 Nov 2020, 6:33:52 pm",
        "prod_name": "Ноутбук",
        "action": "add"
    },
    {
        "time": "09 Nov 2020, 6:33:55 pm",
        "prod_name": "Мышка",
        "action": "add"
    },
    {
        "time": "09 Nov 2020, 6:33:55 pm",
        "prod_name": "Мышка",
        "action": "change"
    },
    {
        "time": "09 Nov 2020, 6:33:57 pm",
        "prod_name": "Мышка",
        "action": "change"
    },
    {
        "time": "09 Nov 2020, 6:33:57 pm",
        "prod_name": "Ноутбук",
        "action": "remove"
    },
    {
        "time": "09 Nov 2020, 6:33:58 pm",
        "prod_name": "Мышка",
        "action": "remove"
    },
    {
        "time": "09 Nov 2020, 7:11:11 pm",
        "prod_name": "Мышка",
        "action": "add"
    },
    {
        "time": "09 Nov 2020, 7:11:12 pm",
        "prod_name": "Мышка",
        "action": "remove"
    },
    {
        "time": "09 Nov 2020, 9:21:01 pm",
        "prod_name": "Keyboard",
        "action": "add"
    },
    {
        "time": "09 Nov 2020, 9:21:02 pm",
        "prod_name": "Keyboard",
        "action": "change"
    },
    {
        "time": "09 Nov 2020, 9:21:04 pm",
        "prod_name": "Keyboard",
        "action": "change"
    },
    {
        "time": "09 Nov 2020, 9:21:04 pm",
        "prod_name": "Keyboard",
        "action": "remove"
    },
    {
        "time": "10 Nov 2020, 9:56:12 am",
        "prod_name": "Ноутбук",
        "action": "add"
    },
    {
        "time": "10 Nov 2020, 9:56:13 am",
        "prod_name": "Gamepad",
        "action": "add"
    },
    {
        "time": "10 Nov 2020, 9:56:14 am",
        "prod_name": "Keyboard",
        "action": "add"
    },
    {
        "time": "10 Nov 2020, 9:56:16 am",
        "prod_name": "Ноутбук",
        "action": "remove"
    },
    {
        "time": "10 Nov 2020, 9:56:17 am",
        "prod_name": "Gamepad",
        "action": "remove"
    },
    {
        "time": "10 Nov 2020, 9:56:17 am",
        "prod_name": "Keyboard",
        "action": "remove"
    },
    {
        "time": "10 Nov 2020, 9:56:25 am",
        "prod_name": "Ноутбук",
        "action": "add"
    },
    {
        "time": "10 Nov 2020, 9:56:26 am",
        "prod_name": "Ноутбук",
        "action": "change"
    },
    {
        "time": "10 Nov 2020, 9:56:27 am",
        "prod_name": "Мышка",
        "action": "add"
    },
    {
        "time": "10 Nov 2020, 9:56:28 am",
        "prod_name": "Мышка",
        "action": "add"
    },
    {
        "time": "10 Nov 2020, 9:56:29 am",
        "prod_name": "Мышка",
        "action": "add"
    },
    {
        "time": "11 Nov 2020, 10:18:13 am",
        "prod_name": "Gamepad",
        "action": "add"
    },
    {
        "time": "11 Nov 2020, 10:18:14 am",
        "prod_name": "Мышка",
        "action": "add"
    },
    {
        "time": "11 Nov 2020, 10:18:16 am",
        "prod_name": "Ноутбук",
        "action": "change"
    },
    {
        "time": "11 Nov 2020, 10:18:16 am",
        "prod_name": "Ноутбук",
        "action": "remove"
    },
    {
        "time": "11 Nov 2020, 10:18:17 am",
        "prod_name": "Мышка",
        "action": "remove"
    },
    {
        "time": "11 Nov 2020, 10:18:17 am",
        "prod_name": "Мышка",
        "action": "remove"
    },
    {
        "time": "11 Nov 2020, 10:18:17 am",
        "prod_name": "Мышка",
        "action": "remove"
    },
    {
        "time": "11 Nov 2020, 10:18:17 am",
        "prod_name": "Gamepad",
        "action": "remove"
    },
    {
        "time": "11 Nov 2020, 10:18:17 am",
        "prod_name": "Мышка",
        "action": "remove"
    },
    {
        "time": "11 Nov 2020, 10:19:58 am",
        "prod_name": "Мышка",
        "action": "add"
    },
    {
        "time": "11 Nov 2020, 10:20:00 am",
        "prod_name": "Мышка",
        "action": "change"
    },
    {
        "time": "11 Nov 2020, 10:20:17 am",
        "prod_name": "Мышка",
        "action": "change"
    },
    {
        "time": "11 Nov 2020, 10:20:19 am",
        "prod_name": "Мышка",
        "action": "change"
    },
    {
        "time": "11 Nov 2020, 10:20:20 am",
        "prod_name": "Мышка",
        "action": "change"
    },
    {
        "time": "11 Nov 2020, 10:20:21 am",
        "prod_name": "Мышка",
        "action": "remove"
    },
    {
        "time": "11 Nov 2020, 10:20:23 am",
        "prod_name": "Мышка",
        "action": "add"
    },
    {
        "time": "11 Nov 2020, 10:21:31 am",
        "prod_name": "Мышка",
        "action": "change"
    },
    {
        "time": "11 Nov 2020, 10:21:34 am",
        "prod_name": "Мышка",
        "action": "change"
    },
    {
        "time": "11 Nov 2020, 10:21:35 am",
        "prod_name": "Мышка",
        "action": "remove"
    },
    {
        "time": "11 Nov 2020, 10:23:05 am",
        "prod_name": "Wamus",
        "action": "remove"
    },
    {
        "time": "11 Nov 2020, 10:23:06 am",
        "prod_name": "T-shirt",
        "action": "remove"
    },
    {
        "time": "11 Nov 2020, 10:23:07 am",
        "prod_name": "Belt",
        "action": "remove"
    },
    {
        "time": "11 Nov 2020, 10:23:07 am",
        "prod_name": "Raincoat",
        "action": "change"
    },
    {
        "time": "11 Nov 2020, 10:23:09 am",
        "prod_name": "Raincoat",
        "action": "remove"
    },
    {
        "time": "11 Nov 2020, 10:23:10 am",
        "prod_name": "Jacket",
        "action": "change"
    },
    {
        "time": "11 Nov 2020, 10:23:11 am",
        "prod_name": "Jacket",
        "action": "remove"
    },
    {
        "time": "11 Nov 2020, 10:28:27 am",
        "prod_name": "Belt",
        "action": "add"
    },
    {
        "time": "11 Nov 2020, 10:28:27 am",
        "prod_name": "T-shirt",
        "action": "add"
    },
    {
        "time": "11 Nov 2020, 10:28:28 am",
        "prod_name": "Jacket",
        "action": "add"
    },
    {
        "time": "11 Nov 2020, 10:28:30 am",
        "prod_name": "T-shirt",
        "action": "remove"
    },
    {
        "time": "11 Nov 2020, 10:28:30 am",
        "prod_name": "Belt",
        "action": "remove"
    },
    {
        "time": "11 Nov 2020, 10:28:32 am",
        "prod_name": "Jacket",
        "action": "remove"
    },
    {
        "time": "11 Nov 2020, 10:28:33 am",
        "prod_name": "Pullover",
        "action": "add"
    },
    {
        "time": "11 Nov 2020, 10:28:34 am",
        "prod_name": "Belt",
        "action": "add"
    },
    {
        "time": "11 Nov 2020, 10:28:36 am",
        "prod_name": "Jacket",
        "action": "add"
    },
    {
        "time": "11 Nov 2020, 10:28:37 am",
        "prod_name": "Jacket",
        "action": "change"
    },
    {
        "time": "11 Nov 2020, 10:28:38 am",
        "prod_name": "Jacket",
        "action": "change"
    },
    {
        "time": "11 Nov 2020, 10:28:39 am",
        "prod_name": "Jacket",
        "action": "remove"
    },
    {
        "time": "11 Nov 2020, 10:28:39 am",
        "prod_name": "Belt",
        "action": "remove"
    },
    {
        "time": "11 Nov 2020, 10:28:40 am",
        "prod_name": "Pullover",
        "action": "remove"
    },
    {
        "time": "11 Nov 2020, 10:31:50 am",
        "prod_name": "Belt",
        "action": "add"
    },
    {
        "time": "11 Nov 2020, 10:32:29 am",
        "prod_name": "Belt",
        "action": "remove"
    },
    {
        "time": "11 Nov 2020, 11:55:44 am",
        "prod_name": "Jacket",
        "action": "add"
    },
    {
        "time": "11 Nov 2020, 11:55:44 am",
        "prod_name": "T-shirt",
        "action": "add"
    },
    {
        "time": "11 Nov 2020, 11:55:46 am",
        "prod_name": "T-shirt",
        "action": "remove"
    },
    {
        "time": "11 Nov 2020, 11:55:47 am",
        "prod_name": "Jacket",
        "action": "remove"
    },
    {
        "time": "11 Nov 2020, 11:55:50 am",
        "prod_name": "Tunic",
        "action": "add"
    },
    {
        "time": "11 Nov 2020, 11:55:51 am",
        "prod_name": "Costume",
        "action": "add"
    },
    {
        "time": "11 Nov 2020, 11:56:18 am",
        "prod_name": "Jacket",
        "action": "add"
    },
    {
        "time": "11 Nov 2020, 11:56:18 am",
        "prod_name": "Raincoat",
        "action": "add"
    },
    {
        "time": "11 Nov 2020, 11:56:20 am",
        "prod_name": "Raincoat",
        "action": "remove"
    },
    {
        "time": "11 Nov 2020, 11:56:21 am",
        "prod_name": "Jacket",
        "action": "remove"
    },
    {
        "time": "11 Nov 2020, 11:56:22 am",
        "prod_name": "Costume",
        "action": "remove"
    },
    {
        "time": "11 Nov 2020, 11:56:22 am",
        "prod_name": "Tunic",
        "action": "remove"
    },
    {
        "time": "11 Nov 2020, 12:04:59 pm",
        "prod_name": "Raincoat",
        "action": "add"
    },
    {
        "time": "11 Nov 2020, 12:05:03 pm",
        "prod_name": "Jacket",
        "action": "add"
    },
    {
        "time": "11 Nov 2020, 12:08:31 pm",
        "prod_name": "Raincoat",
        "action": "change"
    },
    {
        "time": "11 Nov 2020, 12:08:34 pm",
        "prod_name": "Raincoat",
        "action": "change"
    },
    {
        "time": "11 Nov 2020, 12:08:34 pm",
        "prod_name": "Raincoat",
        "action": "remove"
    },
    {
        "time": "11 Nov 2020, 12:08:35 pm",
        "prod_name": "Jacket",
        "action": "remove"
    },
    {
        "time": "11 Nov 2020, 12:10:34 pm",
        "prod_name": "Jacket",
        "action": "add"
    },
    {
        "time": "11 Nov 2020, 12:10:35 pm",
        "prod_name": "T-shirt",
        "action": "add"
    },
    {
        "time": "11 Nov 2020, 12:10:36 pm",
        "prod_name": "Belt",
        "action": "add"
    },
    {
        "time": "11 Nov 2020, 12:10:38 pm",
        "prod_name": "Jacket",
        "action": "remove"
    },
    {
        "time": "11 Nov 2020, 12:10:38 pm",
        "prod_name": "T-shirt",
        "action": "remove"
    },
    {
        "time": "11 Nov 2020, 12:10:39 pm",
        "prod_name": "Belt",
        "action": "remove"
    },
    {
        "time": "11 Nov 2020, 12:10:41 pm",
        "prod_name": "Wamus",
        "action": "add"
    },
    {
        "time": "11 Nov 2020, 12:10:42 pm",
        "prod_name": "T-shirt",
        "action": "add"
    },
    {
        "time": "11 Nov 2020, 12:10:43 pm",
        "prod_name": "Jacket",
        "action": "add"
    },
    {
        "time": "11 Nov 2020, 12:10:44 pm",
        "prod_name": "Jacket",
        "action": "remove"
    },
    {
        "time": "11 Nov 2020, 12:10:45 pm",
        "prod_name": "T-shirt",
        "action": "remove"
    },
    {
        "time": "11 Nov 2020, 12:10:46 pm",
        "prod_name": "Wamus",
        "action": "remove"
    },
    {
        "time": "11 Nov 2020, 12:11:56 pm",
        "prod_name": "Jacket",
        "action": "add"
    },
    {
        "time": "11 Nov 2020, 12:11:58 pm",
        "prod_name": "Jacket",
        "action": "remove"
    },
    {
        "time": "11 Nov 2020, 12:11:59 pm",
        "prod_name": "Belt",
        "action": "add"
    },
    {
        "time": "11 Nov 2020, 12:12:01 pm",
        "prod_name": "Belt",
        "action": "change"
    },
    {
        "time": "11 Nov 2020, 12:12:03 pm",
        "prod_name": "Costume",
        "action": "add"
    },
    {
        "time": "11 Nov 2020, 12:12:03 pm",
        "prod_name": "Costume",
        "action": "change"
    },
    {
        "time": "11 Nov 2020, 12:12:04 pm",
        "prod_name": "Costume",
        "action": "change"
    },
    {
        "time": "11 Nov 2020, 12:12:04 pm",
        "prod_name": "Costume",
        "action": "change"
    },
    {
        "time": "11 Nov 2020, 12:12:05 pm",
        "prod_name": "Costume",
        "action": "change"
    },
    {
        "time": "11 Nov 2020, 12:12:05 pm",
        "prod_name": "Costume",
        "action": "change"
    },
    {
        "time": "11 Nov 2020, 12:12:06 pm",
        "prod_name": "Costume",
        "action": "change"
    },
    {
        "time": "11 Nov 2020, 12:12:06 pm",
        "prod_name": "Costume",
        "action": "remove"
    },
    {
        "time": "11 Nov 2020, 12:12:07 pm",
        "prod_name": "Belt",
        "action": "change"
    },
    {
        "time": "11 Nov 2020, 12:12:07 pm",
        "prod_name": "Belt",
        "action": "remove"
    },
    {
        "time": "11 Nov 2020, 12:17:56 pm",
        "prod_name": "T-shirt",
        "action": "add"
    },
    {
        "time": "11 Nov 2020, 12:17:57 pm",
        "prod_name": "Belt",
        "action": "add"
    },
    {
        "time": "11 Nov 2020, 12:17:58 pm",
        "prod_name": "Jacket",
        "action": "add"
    },
    {
        "time": "11 Nov 2020, 12:17:59 pm",
        "prod_name": "Raincoat",
        "action": "add"
    },
    {
        "time": "11 Nov 2020, 12:18:00 pm",
        "prod_name": "Wamus",
        "action": "add"
    },
    {
        "time": "11 Nov 2020, 12:18:01 pm",
        "prod_name": "Costume",
        "action": "add"
    },
    {
        "time": "11 Nov 2020, 12:18:03 pm",
        "prod_name": "T-shirt",
        "action": "remove"
    },
    {
        "time": "11 Nov 2020, 12:18:03 pm",
        "prod_name": "Belt",
        "action": "remove"
    },
    {
        "time": "11 Nov 2020, 12:18:03 pm",
        "prod_name": "Jacket",
        "action": "remove"
    },
    {
        "time": "11 Nov 2020, 12:18:03 pm",
        "prod_name": "Raincoat",
        "action": "remove"
    },
    {
        "time": "11 Nov 2020, 12:18:03 pm",
        "prod_name": "Wamus",
        "action": "remove"
    },
    {
        "time": "11 Nov 2020, 12:18:03 pm",
        "prod_name": "Costume",
        "action": "remove"
    },
    {
        "time": "11 Nov 2020, 12:18:05 pm",
        "prod_name": "T-shirt",
        "action": "add"
    },
    {
        "time": "11 Nov 2020, 12:18:05 pm",
        "prod_name": "T-shirt",
        "action": "change"
    },
    {
        "time": "11 Nov 2020, 12:18:05 pm",
        "prod_name": "T-shirt",
        "action": "change"
    },
    {
        "time": "11 Nov 2020, 12:18:05 pm",
        "prod_name": "T-shirt",
        "action": "change"
    },
    {
        "time": "11 Nov 2020, 12:18:05 pm",
        "prod_name": "T-shirt",
        "action": "change"
    },
    {
        "time": "11 Nov 2020, 12:18:06 pm",
        "prod_name": "T-shirt",
        "action": "change"
    },
    {
        "time": "11 Nov 2020, 12:18:07 pm",
        "prod_name": "T-shirt",
        "action": "change"
    },
    {
        "time": "11 Nov 2020, 12:18:07 pm",
        "prod_name": "T-shirt",
        "action": "change"
    },
    {
        "time": "11 Nov 2020, 12:18:07 pm",
        "prod_name": "T-shirt",
        "action": "change"
    },
    {
        "time": "11 Nov 2020, 12:18:07 pm",
        "prod_name": "T-shirt",
        "action": "remove"
    },
    {
        "time": "11 Nov 2020, 12:26:34 pm",
        "prod_name": "Jacket",
        "action": "add"
    },
    {
        "time": "11 Nov 2020, 12:26:35 pm",
        "prod_name": "T-shirt",
        "action": "add"
    },
    {
        "time": "11 Nov 2020, 12:26:36 pm",
        "prod_name": "Belt",
        "action": "add"
    },
    {
        "time": "11 Nov 2020, 12:26:37 pm",
        "prod_name": "Jacket",
        "action": "remove"
    },
    {
        "time": "11 Nov 2020, 12:26:38 pm",
        "prod_name": "T-shirt",
        "action": "remove"
    },
    {
        "time": "11 Nov 2020, 12:26:38 pm",
        "prod_name": "Belt",
        "action": "remove"
    },
    {
        "time": "11 Nov 2020, 12:26:41 pm",
        "prod_name": "Pullover",
        "action": "add"
    },
    {
        "time": "11 Nov 2020, 12:26:42 pm",
        "prod_name": "Wamus",
        "action": "add"
    },
    {
        "time": "11 Nov 2020, 12:26:42 pm",
        "prod_name": "Costume",
        "action": "add"
    },
    {
        "time": "11 Nov 2020, 12:26:43 pm",
        "prod_name": "Tunic",
        "action": "add"
    },
    {
        "time": "11 Nov 2020, 12:26:44 pm",
        "prod_name": "Belt",
        "action": "add"
    },
    {
        "time": "11 Nov 2020, 12:26:45 pm",
        "prod_name": "T-shirt",
        "action": "add"
    },
    {
        "time": "11 Nov 2020, 12:26:46 pm",
        "prod_name": "Jacket",
        "action": "add"
    },
    {
        "time": "11 Nov 2020, 12:26:46 pm",
        "prod_name": "Raincoat",
        "action": "add"
    },
    {
        "time": "11 Nov 2020, 12:26:49 pm",
        "prod_name": "Pullover",
        "action": "remove"
    },
    {
        "time": "11 Nov 2020, 12:26:49 pm",
        "prod_name": "Wamus",
        "action": "remove"
    },
    {
        "time": "11 Nov 2020, 12:26:49 pm",
        "prod_name": "Costume",
        "action": "remove"
    },
    {
        "time": "11 Nov 2020, 12:26:50 pm",
        "prod_name": "Tunic",
        "action": "remove"
    },
    {
        "time": "11 Nov 2020, 12:26:50 pm",
        "prod_name": "Belt",
        "action": "remove"
    },
    {
        "time": "11 Nov 2020, 12:26:50 pm",
        "prod_name": "T-shirt",
        "action": "remove"
    },
    {
        "time": "11 Nov 2020, 12:26:50 pm",
        "prod_name": "Jacket",
        "action": "remove"
    },
    {
        "time": "11 Nov 2020, 12:26:50 pm",
        "prod_name": "Raincoat",
        "action": "remove"
    },
    {
        "time": "11 Nov 2020, 12:26:51 pm",
        "prod_name": "T-shirt",
        "action": "add"
    },
    {
        "time": "11 Nov 2020, 12:26:52 pm",
        "prod_name": "Belt",
        "action": "add"
    },
    {
        "time": "11 Nov 2020, 12:26:53 pm",
        "prod_name": "Belt",
        "action": "change"
    },
    {
        "time": "11 Nov 2020, 12:26:53 pm",
        "prod_name": "Belt",
        "action": "change"
    },
    {
        "time": "11 Nov 2020, 12:26:53 pm",
        "prod_name": "Belt",
        "action": "change"
    },
    {
        "time": "11 Nov 2020, 12:26:54 pm",
        "prod_name": "Belt",
        "action": "change"
    },
    {
        "time": "11 Nov 2020, 12:26:54 pm",
        "prod_name": "Belt",
        "action": "change"
    },
    {
        "time": "11 Nov 2020, 12:26:54 pm",
        "prod_name": "Belt",
        "action": "change"
    },
    {
        "time": "11 Nov 2020, 12:26:55 pm",
        "prod_name": "T-shirt",
        "action": "remove"
    },
    {
        "time": "11 Nov 2020, 12:26:55 pm",
        "prod_name": "Belt",
        "action": "remove"
    },
    {
        "time": "11 Nov 2020, 12:26:59 pm",
        "prod_name": "Pullover",
        "action": "add"
    },
    {
        "time": "11 Nov 2020, 12:27:00 pm",
        "prod_name": "T-shirt",
        "action": "add"
    },
    {
        "time": "11 Nov 2020, 12:27:01 pm",
        "prod_name": "Jacket",
        "action": "add"
    },
    {
        "time": "11 Nov 2020, 12:27:01 pm",
        "prod_name": "Jacket",
        "action": "change"
    },
    {
        "time": "11 Nov 2020, 12:27:02 pm",
        "prod_name": "Jacket",
        "action": "change"
    },
    {
        "time": "11 Nov 2020, 12:27:02 pm",
        "prod_name": "Jacket",
        "action": "change"
    },
    {
        "time": "11 Nov 2020, 12:27:04 pm",
        "prod_name": "Pullover",
        "action": "remove"
    },
    {
        "time": "11 Nov 2020, 12:27:04 pm",
        "prod_name": "T-shirt",
        "action": "remove"
    },
    {
        "time": "11 Nov 2020, 12:27:04 pm",
        "prod_name": "Jacket",
        "action": "change"
    },
    {
        "time": "11 Nov 2020, 12:27:05 pm",
        "prod_name": "Jacket",
        "action": "change"
    },
    {
        "time": "11 Nov 2020, 12:27:06 pm",
        "prod_name": "Jacket",
        "action": "change"
    },
    {
        "time": "11 Nov 2020, 12:27:06 pm",
        "prod_name": "Jacket",
        "action": "remove"
    },
    {
        "time": "11 Nov 2020, 12:28:27 pm",
        "prod_name": "Belt",
        "action": "add"
    },
    {
        "time": "11 Nov 2020, 12:29:27 pm",
        "prod_name": "T-shirt",
        "action": "add"
    },
    {
        "time": "11 Nov 2020, 12:29:29 pm",
        "prod_name": "Belt",
        "action": "remove"
    },
    {
        "time": "11 Nov 2020, 12:29:30 pm",
        "prod_name": "T-shirt",
        "action": "remove"
    },
    {
        "time": "11 Nov 2020, 12:31:36 pm",
        "prod_name": "Jacket",
        "action": "add"
    },
    {
        "time": "11 Nov 2020, 12:31:37 pm",
        "prod_name": "Jacket",
        "action": "change"
    },
    {
        "time": "11 Nov 2020, 12:31:37 pm",
        "prod_name": "Jacket",
        "action": "change"
    },
    {
        "time": "11 Nov 2020, 12:31:38 pm",
        "prod_name": "T-shirt",
        "action": "add"
    },
    {
        "time": "11 Nov 2020, 12:31:38 pm",
        "prod_name": "T-shirt",
        "action": "change"
    },
    {
        "time": "11 Nov 2020, 12:31:38 pm",
        "prod_name": "T-shirt",
        "action": "change"
    },
    {
        "time": "11 Nov 2020, 12:31:38 pm",
        "prod_name": "T-shirt",
        "action": "change"
    },
    {
        "time": "11 Nov 2020, 12:31:40 pm",
        "prod_name": "Jacket",
        "action": "change"
    },
    {
        "time": "11 Nov 2020, 12:31:40 pm",
        "prod_name": "Jacket",
        "action": "change"
    },
    {
        "time": "11 Nov 2020, 12:31:40 pm",
        "prod_name": "Jacket",
        "action": "remove"
    },
    {
        "time": "11 Nov 2020, 12:31:40 pm",
        "prod_name": "T-shirt",
        "action": "change"
    },
    {
        "time": "11 Nov 2020, 12:31:41 pm",
        "prod_name": "T-shirt",
        "action": "change"
    },
    {
        "time": "11 Nov 2020, 12:31:41 pm",
        "prod_name": "T-shirt",
        "action": "change"
    },
    {
        "time": "11 Nov 2020, 12:31:41 pm",
        "prod_name": "T-shirt",
        "action": "remove"
    },
    {
        "time": "11 Nov 2020, 12:34:16 pm",
        "prod_name": "Jacket",
        "action": "add"
    },
    {
        "time": "11 Nov 2020, 12:34:17 pm",
        "prod_name": "T-shirt",
        "action": "add"
    },
    {
        "time": "11 Nov 2020, 12:34:17 pm",
        "prod_name": "Jacket",
        "action": "remove"
    },
    {
        "time": "11 Nov 2020, 12:34:18 pm",
        "prod_name": "T-shirt",
        "action": "remove"
    },
    {
        "time": "11 Nov 2020, 12:46:42 pm",
        "prod_name": "Jacket",
        "action": "add"
    },
    {
        "time": "11 Nov 2020, 12:46:43 pm",
        "prod_name": "T-shirt",
        "action": "add"
    },
    {
        "time": "11 Nov 2020, 12:46:44 pm",
        "prod_name": "Belt",
        "action": "add"
    },
    {
        "time": "11 Nov 2020, 12:46:45 pm",
        "prod_name": "Jacket",
        "action": "remove"
    },
    {
        "time": "11 Nov 2020, 12:46:45 pm",
        "prod_name": "T-shirt",
        "action": "remove"
    },
    {
        "time": "11 Nov 2020, 12:46:46 pm",
        "prod_name": "Belt",
        "action": "remove"
    },
    {
        "time": "11 Nov 2020, 12:46:48 pm",
        "prod_name": "Tunic",
        "action": "add"
    },
    {
        "time": "11 Nov 2020, 12:46:49 pm",
        "prod_name": "Costume",
        "action": "add"
    },
    {
        "time": "11 Nov 2020, 12:46:50 pm",
        "prod_name": "Wamus",
        "action": "add"
    },
    {
        "time": "11 Nov 2020, 12:46:51 pm",
        "prod_name": "Wamus",
        "action": "remove"
    },
    {
        "time": "11 Nov 2020, 12:46:52 pm",
        "prod_name": "Costume",
        "action": "remove"
    },
    {
        "time": "11 Nov 2020, 12:46:53 pm",
        "prod_name": "Tunic",
        "action": "remove"
    },
    {
        "time": "11 Nov 2020, 12:53:50 pm",
        "prod_name": "Jacket",
        "action": "add"
    },
    {
        "time": "11 Nov 2020, 12:53:51 pm",
        "prod_name": "T-shirt",
        "action": "add"
    },
    {
        "time": "11 Nov 2020, 12:53:54 pm",
        "prod_name": "Wamus",
        "action": "add"
    },
    {
        "time": "11 Nov 2020, 12:53:55 pm",
        "prod_name": "Pullover",
        "action": "add"
    },
    {
        "time": "11 Nov 2020, 12:53:56 pm",
        "prod_name": "Raincoat",
        "action": "add"
    },
    {
        "time": "11 Nov 2020, 12:53:57 pm",
        "prod_name": "Belt",
        "action": "add"
    },
    {
        "time": "11 Nov 2020, 12:54:40 pm",
        "prod_name": "Jacket",
        "action": "remove"
    },
    {
        "time": "11 Nov 2020, 12:54:40 pm",
        "prod_name": "T-shirt",
        "action": "remove"
    },
    {
        "time": "11 Nov 2020, 12:54:41 pm",
        "prod_name": "Wamus",
        "action": "remove"
    },
    {
        "time": "11 Nov 2020, 12:54:41 pm",
        "prod_name": "Pullover",
        "action": "remove"
    },
    {
        "time": "11 Nov 2020, 12:54:41 pm",
        "prod_name": "Raincoat",
        "action": "remove"
    },
    {
        "time": "11 Nov 2020, 12:54:41 pm",
        "prod_name": "Belt",
        "action": "remove"
    },
    {
        "time": "11 Nov 2020, 12:55:26 pm",
        "prod_name": "T-shirt",
        "action": "add"
    },
    {
        "time": "11 Nov 2020, 12:55:31 pm",
        "prod_name": "T-shirt",
        "action": "remove"
    },
    {
        "time": "11 Nov 2020, 12:57:25 pm",
        "prod_name": "T-shirt",
        "action": "add"
    },
    {
        "time": "11 Nov 2020, 12:57:27 pm",
        "prod_name": "T-shirt",
        "action": "remove"
    },
    {
        "time": "11 Nov 2020, 12:57:28 pm",
        "prod_name": "Belt",
        "action": "add"
    },
    {
        "time": "11 Nov 2020, 12:57:28 pm",
        "prod_name": "Belt",
        "action": "change"
    },
    {
        "time": "11 Nov 2020, 12:57:28 pm",
        "prod_name": "Belt",
        "action": "change"
    },
    {
        "time": "11 Nov 2020, 12:57:29 pm",
        "prod_name": "Belt",
        "action": "change"
    },
    {
        "time": "11 Nov 2020, 12:57:29 pm",
        "prod_name": "Belt",
        "action": "change"
    },
    {
        "time": "11 Nov 2020, 12:57:30 pm",
        "prod_name": "Belt",
        "action": "change"
    },
    {
        "time": "11 Nov 2020, 12:57:30 pm",
        "prod_name": "Belt",
        "action": "change"
    },
    {
        "time": "11 Nov 2020, 12:57:30 pm",
        "prod_name": "Belt",
        "action": "change"
    },
    {
        "time": "11 Nov 2020, 12:57:30 pm",
        "prod_name": "Belt",
        "action": "change"
    },
    {
        "time": "11 Nov 2020, 12:57:31 pm",
        "prod_name": "Belt",
        "action": "remove"
    },
    {
        "time": "11 Nov 2020, 1:02:51 pm",
        "prod_name": "T-shirt",
        "action": "add"
    },
    {
        "time": "11 Nov 2020, 1:02:52 pm",
        "prod_name": "Belt",
        "action": "add"
    },
    {
        "time": "11 Nov 2020, 1:02:52 pm",
        "prod_name": "Jacket",
        "action": "add"
    },
    {
        "time": "11 Nov 2020, 1:02:54 pm",
        "prod_name": "Costume",
        "action": "add"
    },
    {
        "time": "11 Nov 2020, 1:02:55 pm",
        "prod_name": "Costume",
        "action": "change"
    },
    {
        "time": "11 Nov 2020, 1:02:55 pm",
        "prod_name": "Costume",
        "action": "change"
    },
    {
        "time": "11 Nov 2020, 1:02:55 pm",
        "prod_name": "Costume",
        "action": "change"
    },
    {
        "time": "11 Nov 2020, 1:02:56 pm",
        "prod_name": "Costume",
        "action": "change"
    },
    {
        "time": "11 Nov 2020, 1:02:56 pm",
        "prod_name": "Costume",
        "action": "change"
    },
    {
        "time": "11 Nov 2020, 1:02:56 pm",
        "prod_name": "Costume",
        "action": "change"
    },
    {
        "time": "11 Nov 2020, 1:02:57 pm",
        "prod_name": "Costume",
        "action": "remove"
    },
    {
        "time": "11 Nov 2020, 1:02:58 pm",
        "prod_name": "Jacket",
        "action": "remove"
    },
    {
        "time": "11 Nov 2020, 1:03:00 pm",
        "prod_name": "Belt",
        "action": "remove"
    },
    {
        "time": "11 Nov 2020, 1:03:02 pm",
        "prod_name": "T-shirt",
        "action": "remove"
    },
    {
        "time": "11 Nov 2020, 1:03:52 pm",
        "prod_name": "T-shirt",
        "action": "add"
    },
    {
        "time": "11 Nov 2020, 1:03:53 pm",
        "prod_name": "Jacket",
        "action": "add"
    },
    {
        "time": "11 Nov 2020, 1:03:54 pm",
        "prod_name": "Wamus",
        "action": "add"
    },
    {
        "time": "11 Nov 2020, 1:03:56 pm",
        "prod_name": "Tunic",
        "action": "add"
    },
    {
        "time": "11 Nov 2020, 1:03:56 pm",
        "prod_name": "Tunic",
        "action": "change"
    },
    {
        "time": "11 Nov 2020, 1:03:56 pm",
        "prod_name": "Tunic",
        "action": "change"
    },
    {
        "time": "11 Nov 2020, 1:03:58 pm",
        "prod_name": "T-shirt",
        "action": "remove"
    },
    {
        "time": "11 Nov 2020, 1:03:59 pm",
        "prod_name": "Jacket",
        "action": "remove"
    },
    {
        "time": "11 Nov 2020, 1:03:59 pm",
        "prod_name": "Wamus",
        "action": "remove"
    },
    {
        "time": "11 Nov 2020, 1:03:59 pm",
        "prod_name": "Tunic",
        "action": "change"
    },
    {
        "time": "11 Nov 2020, 1:03:59 pm",
        "prod_name": "Tunic",
        "action": "change"
    },
    {
        "time": "11 Nov 2020, 1:04:00 pm",
        "prod_name": "Tunic",
        "action": "remove"
    },
    {
        "time": "11 Nov 2020, 1:05:43 pm",
        "prod_name": "Costume",
        "action": "add"
    },
    {
        "time": "11 Nov 2020, 1:07:47 pm",
        "prod_name": "Wamus",
        "action": "add"
    },
    {
        "time": "11 Nov 2020, 1:07:47 pm",
        "prod_name": "Wamus",
        "action": "change"
    },
    {
        "time": "11 Nov 2020, 1:07:48 pm",
        "prod_name": "Wamus",
        "action": "change"
    },
    {
        "time": "11 Nov 2020, 1:07:48 pm",
        "prod_name": "Wamus",
        "action": "change"
    },
    {
        "time": "11 Nov 2020, 1:07:48 pm",
        "prod_name": "Wamus",
        "action": "change"
    },
    {
        "time": "11 Nov 2020, 1:07:50 pm",
        "prod_name": "Costume",
        "action": "remove"
    },
    {
        "time": "11 Nov 2020, 1:07:50 pm",
        "prod_name": "Wamus",
        "action": "change"
    },
    {
        "time": "11 Nov 2020, 1:07:51 pm",
        "prod_name": "Wamus",
        "action": "change"
    },
    {
        "time": "11 Nov 2020, 1:07:51 pm",
        "prod_name": "Wamus",
        "action": "change"
    },
    {
        "time": "11 Nov 2020, 1:07:51 pm",
        "prod_name": "Wamus",
        "action": "change"
    },
    {
        "time": "11 Nov 2020, 1:07:51 pm",
        "prod_name": "Wamus",
        "action": "remove"
    },
    {
        "time": "11 Nov 2020, 1:11:31 pm",
        "prod_name": "Raincoat",
        "action": "add"
    },
    {
        "time": "11 Nov 2020, 1:11:33 pm",
        "prod_name": "Raincoat",
        "action": "change"
    },
    {
        "time": "11 Nov 2020, 1:11:35 pm",
        "prod_name": "Jacket",
        "action": "add"
    },
    {
        "time": "11 Nov 2020, 1:15:30 pm",
        "prod_name": "Raincoat",
        "action": "change"
    },
    {
        "time": "11 Nov 2020, 1:15:31 pm",
        "prod_name": "Wamus",
        "action": "add"
    },
    {
        "time": "11 Nov 2020, 1:15:33 pm",
        "prod_name": "Jacket",
        "action": "change"
    },
    {
        "time": "11 Nov 2020, 1:15:34 pm",
        "prod_name": "T-shirt",
        "action": "add"
    },
    {
        "time": "11 Nov 2020, 1:15:37 pm",
        "prod_name": "Raincoat",
        "action": "change"
    },
    {
        "time": "11 Nov 2020, 1:15:38 pm",
        "prod_name": "Raincoat",
        "action": "change"
    },
    {
        "time": "11 Nov 2020, 1:15:38 pm",
        "prod_name": "Raincoat",
        "action": "remove"
    },
    {
        "time": "11 Nov 2020, 1:15:38 pm",
        "prod_name": "Jacket",
        "action": "change"
    },
    {
        "time": "11 Nov 2020, 1:15:38 pm",
        "prod_name": "Jacket",
        "action": "remove"
    },
    {
        "time": "11 Nov 2020, 1:15:38 pm",
        "prod_name": "Wamus",
        "action": "remove"
    },
    {
        "time": "11 Nov 2020, 1:15:39 pm",
        "prod_name": "T-shirt",
        "action": "remove"
    },
    {
        "time": "11 Nov 2020, 1:29:17 pm",
        "prod_name": "T-shirt",
        "action": "add"
    },
    {
        "time": "11 Nov 2020, 1:29:18 pm",
        "prod_name": "Belt",
        "action": "add"
    },
    {
        "time": "11 Nov 2020, 1:29:19 pm",
        "prod_name": "Jacket",
        "action": "add"
    },
    {
        "time": "11 Nov 2020, 1:29:23 pm",
        "prod_name": "T-shirt",
        "action": "remove"
    },
    {
        "time": "11 Nov 2020, 1:29:24 pm",
        "prod_name": "Belt",
        "action": "remove"
    },
    {
        "time": "11 Nov 2020, 1:29:24 pm",
        "prod_name": "Jacket",
        "action": "remove"
    },
    {
        "time": "11 Nov 2020, 1:29:25 pm",
        "prod_name": "Pullover",
        "action": "add"
    },
    {
        "time": "11 Nov 2020, 1:29:25 pm",
        "prod_name": "Pullover",
        "action": "change"
    },
    {
        "time": "11 Nov 2020, 1:29:25 pm",
        "prod_name": "Pullover",
        "action": "change"
    },
    {
        "time": "11 Nov 2020, 1:29:25 pm",
        "prod_name": "Pullover",
        "action": "change"
    },
    {
        "time": "11 Nov 2020, 1:29:26 pm",
        "prod_name": "Pullover",
        "action": "change"
    },
    {
        "time": "11 Nov 2020, 1:29:27 pm",
        "prod_name": "Pullover",
        "action": "change"
    },
    {
        "time": "11 Nov 2020, 1:29:27 pm",
        "prod_name": "Pullover",
        "action": "change"
    },
    {
        "time": "11 Nov 2020, 1:29:27 pm",
        "prod_name": "Pullover",
        "action": "change"
    },
    {
        "time": "11 Nov 2020, 1:29:27 pm",
        "prod_name": "Pullover",
        "action": "change"
    },
    {
        "time": "11 Nov 2020, 1:29:28 pm",
        "prod_name": "Pullover",
        "action": "remove"
    },
    {
        "time": "11 Nov 2020, 1:33:03 pm",
        "prod_name": "Jacket",
        "action": "add"
    },
    {
        "time": "11 Nov 2020, 1:33:04 pm",
        "prod_name": "T-shirt",
        "action": "add"
    },
    {
        "time": "11 Nov 2020, 1:33:05 pm",
        "prod_name": "Jacket",
        "action": "remove"
    },
    {
        "time": "11 Nov 2020, 1:33:05 pm",
        "prod_name": "T-shirt",
        "action": "remove"
    },
    {
        "time": "11 Nov 2020, 1:33:07 pm",
        "prod_name": "Belt",
        "action": "add"
    },
    {
        "time": "11 Nov 2020, 1:33:07 pm",
        "prod_name": "Belt",
        "action": "change"
    },
    {
        "time": "11 Nov 2020, 1:33:07 pm",
        "prod_name": "Belt",
        "action": "change"
    },
    {
        "time": "11 Nov 2020, 1:33:07 pm",
        "prod_name": "Belt",
        "action": "change"
    },
    {
        "time": "11 Nov 2020, 1:33:08 pm",
        "prod_name": "Belt",
        "action": "change"
    },
    {
        "time": "11 Nov 2020, 1:33:08 pm",
        "prod_name": "Belt",
        "action": "change"
    },
    {
        "time": "11 Nov 2020, 1:33:09 pm",
        "prod_name": "Belt",
        "action": "change"
    },
    {
        "time": "11 Nov 2020, 1:33:09 pm",
        "prod_name": "Belt",
        "action": "remove"
    },
    {
        "time": "11 Nov 2020, 1:35:38 pm",
        "prod_name": "Tunic",
        "action": "add"
    },
    {
        "time": "11 Nov 2020, 1:35:40 pm",
        "prod_name": "Tunic",
        "action": "remove"
    },
    {
        "time": "11 Nov 2020, 1:35:41 pm",
        "prod_name": "Belt",
        "action": "add"
    },
    {
        "time": "11 Nov 2020, 1:35:41 pm",
        "prod_name": "Belt",
        "action": "change"
    },
    {
        "time": "11 Nov 2020, 1:35:41 pm",
        "prod_name": "Belt",
        "action": "change"
    },
    {
        "time": "11 Nov 2020, 1:35:42 pm",
        "prod_name": "Belt",
        "action": "change"
    },
    {
        "time": "11 Nov 2020, 1:35:42 pm",
        "prod_name": "Belt",
        "action": "change"
    },
    {
        "time": "11 Nov 2020, 1:35:42 pm",
        "prod_name": "Belt",
        "action": "remove"
    },
    {
        "time": "11 Nov 2020, 1:43:50 pm",
        "prod_name": "T-shirt",
        "action": "add"
    },
    {
        "time": "11 Nov 2020, 1:43:51 pm",
        "prod_name": "Belt",
        "action": "add"
    },
    {
        "time": "11 Nov 2020, 1:43:52 pm",
        "prod_name": "Wamus",
        "action": "add"
    },
    {
        "time": "11 Nov 2020, 1:43:53 pm",
        "prod_name": "Raincoat",
        "action": "add"
    },
    {
        "time": "11 Nov 2020, 1:43:54 pm",
        "prod_name": "T-shirt",
        "action": "change"
    },
    {
        "time": "11 Nov 2020, 1:43:55 pm",
        "prod_name": "T-shirt",
        "action": "change"
    },
    {
        "time": "11 Nov 2020, 1:43:56 pm",
        "prod_name": "T-shirt",
        "action": "remove"
    },
    {
        "time": "11 Nov 2020, 1:43:56 pm",
        "prod_name": "Belt",
        "action": "remove"
    },
    {
        "time": "11 Nov 2020, 1:43:56 pm",
        "prod_name": "Wamus",
        "action": "remove"
    },
    {
        "time": "11 Nov 2020, 1:43:56 pm",
        "prod_name": "Raincoat",
        "action": "remove"
    },
    {
        "time": "11 Nov 2020, 1:54:50 pm",
        "prod_name": "Tunic",
        "action": "add"
    },
    {
        "time": "11 Nov 2020, 1:54:51 pm",
        "prod_name": "Costume",
        "action": "add"
    },
    {
        "time": "11 Nov 2020, 1:54:52 pm",
        "prod_name": "Wamus",
        "action": "add"
    },
    {
        "time": "11 Nov 2020, 1:54:53 pm",
        "prod_name": "T-shirt",
        "action": "add"
    },
    {
        "time": "11 Nov 2020, 2:23:32 pm",
        "prod_name": "T-shirt",
        "action": "change"
    },
    {
        "time": "11 Nov 2020, 2:23:33 pm",
        "prod_name": "Belt",
        "action": "add"
    },
    {
        "time": "11 Nov 2020, 2:23:34 pm",
        "prod_name": "Tunic",
        "action": "change"
    },
    {
        "time": "11 Nov 2020, 2:23:37 pm",
        "prod_name": "Tunic",
        "action": "change"
    },
    {
        "time": "11 Nov 2020, 2:23:37 pm",
        "prod_name": "Tunic",
        "action": "remove"
    },
    {
        "time": "11 Nov 2020, 2:23:37 pm",
        "prod_name": "Costume",
        "action": "remove"
    },
    {
        "time": "11 Nov 2020, 2:23:37 pm",
        "prod_name": "Wamus",
        "action": "remove"
    },
    {
        "time": "11 Nov 2020, 2:23:37 pm",
        "prod_name": "T-shirt",
        "action": "change"
    },
    {
        "time": "11 Nov 2020, 2:23:38 pm",
        "prod_name": "T-shirt",
        "action": "remove"
    },
    {
        "time": "11 Nov 2020, 2:23:38 pm",
        "prod_name": "Belt",
        "action": "remove"
    },
    {
        "time": "11 Nov 2020, 2:40:35 pm",
        "prod_name": "Belt",
        "action": "add"
    },
    {
        "time": "11 Nov 2020, 2:40:36 pm",
        "prod_name": "T-shirt",
        "action": "add"
    },
    {
        "time": "11 Nov 2020, 2:40:37 pm",
        "prod_name": "Jacket",
        "action": "add"
    },
    {
        "time": "11 Nov 2020, 2:45:45 pm",
        "prod_name": "Jacket",
        "action": "remove"
    },
    {
        "time": "11 Nov 2020, 2:45:46 pm",
        "prod_name": "T-shirt",
        "action": "remove"
    },
    {
        "time": "11 Nov 2020, 2:45:47 pm",
        "prod_name": "Belt",
        "action": "remove"
    },
    {
        "time": "11 Nov 2020, 2:55:55 pm",
        "prod_name": "Belt",
        "action": "add"
    },
    {
        "time": "11 Nov 2020, 2:55:56 pm",
        "prod_name": "T-shirt",
        "action": "add"
    },
    {
        "time": "11 Nov 2020, 2:55:57 pm",
        "prod_name": "Jacket",
        "action": "add"
    },
    {
        "time": "11 Nov 2020, 2:56:13 pm",
        "prod_name": "Jacket",
        "action": "remove"
    },
    {
        "time": "11 Nov 2020, 2:56:13 pm",
        "prod_name": "T-shirt",
        "action": "remove"
    },
    {
        "time": "11 Nov 2020, 2:56:14 pm",
        "prod_name": "Belt",
        "action": "remove"
    },
    {
        "time": "11 Nov 2020, 2:58:22 pm",
        "prod_name": "Belt",
        "action": "add"
    },
    {
        "time": "11 Nov 2020, 2:58:23 pm",
        "prod_name": "T-shirt",
        "action": "add"
    },
    {
        "time": "11 Nov 2020, 2:58:24 pm",
        "prod_name": "Jacket",
        "action": "add"
    },
    {
        "time": "11 Nov 2020, 2:58:24 pm",
        "prod_name": "T-shirt",
        "action": "remove"
    },
    {
        "time": "11 Nov 2020, 2:58:26 pm",
        "prod_name": "Belt",
        "action": "remove"
    },
    {
        "time": "11 Nov 2020, 2:58:26 pm",
        "prod_name": "Jacket",
        "action": "remove"
    },
    {
        "time": "11 Nov 2020, 2:58:27 pm",
        "prod_name": "Belt",
        "action": "add"
    },
    {
        "time": "11 Nov 2020, 2:58:27 pm",
        "prod_name": "Belt",
        "action": "change"
    },
    {
        "time": "11 Nov 2020, 2:58:27 pm",
        "prod_name": "Belt",
        "action": "change"
    },
    {
        "time": "11 Nov 2020, 2:58:27 pm",
        "prod_name": "Belt",
        "action": "change"
    },
    {
        "time": "11 Nov 2020, 2:58:28 pm",
        "prod_name": "Belt",
        "action": "change"
    },
    {
        "time": "11 Nov 2020, 2:58:28 pm",
        "prod_name": "Belt",
        "action": "change"
    },
    {
        "time": "11 Nov 2020, 2:58:29 pm",
        "prod_name": "Belt",
        "action": "change"
    },
    {
        "time": "11 Nov 2020, 2:58:29 pm",
        "prod_name": "Belt",
        "action": "remove"
    },
    {
        "time": "11 Nov 2020, 4:30:29 pm",
        "prod_name": "Belt",
        "action": "add"
    },
    {
        "time": "11 Nov 2020, 4:37:36 pm",
        "prod_name": "Belt",
        "action": "change"
    },
    {
        "time": "11 Nov 2020, 4:37:37 pm",
        "prod_name": "T-shirt",
        "action": "add"
    },
    {
        "time": "11 Nov 2020, 4:37:38 pm",
        "prod_name": "Jacket",
        "action": "add"
    },
    {
        "time": "11 Nov 2020, 4:39:24 pm",
        "prod_name": "T-shirt",
        "action": "change"
    },
    {
        "time": "11 Nov 2020, 4:39:25 pm",
        "prod_name": "Jacket",
        "action": "change"
    },
    {
        "time": "11 Nov 2020, 4:39:27 pm",
        "prod_name": "Costume",
        "action": "add"
    },
    {
        "time": "11 Nov 2020, 4:39:29 pm",
        "prod_name": "T-shirt",
        "action": "change"
    },
    {
        "time": "11 Nov 2020, 4:39:30 pm",
        "prod_name": "Jacket",
        "action": "change"
    },
    {
        "time": "11 Nov 2020, 4:39:31 pm",
        "prod_name": "T-shirt",
        "action": "remove"
    },
    {
        "time": "11 Nov 2020, 4:39:32 pm",
        "prod_name": "Jacket",
        "action": "remove"
    },
    {
        "time": "11 Nov 2020, 4:39:33 pm",
        "prod_name": "Belt",
        "action": "change"
    },
    {
        "time": "11 Nov 2020, 4:39:34 pm",
        "prod_name": "Costume",
        "action": "remove"
    },
    {
        "time": "11 Nov 2020, 4:39:35 pm",
        "prod_name": "Belt",
        "action": "remove"
    },
    {
        "time": "11 Nov 2020, 4:43:51 pm",
        "prod_name": "T-shirt",
        "action": "add"
    },
    {
        "time": "11 Nov 2020, 4:43:52 pm",
        "prod_name": "Belt",
        "action": "add"
    },
    {
        "time": "11 Nov 2020, 4:43:53 pm",
        "prod_name": "Jacket",
        "action": "add"
    },
    {
        "time": "11 Nov 2020, 4:44:32 pm",
        "prod_name": "Belt",
        "action": "remove"
    },
    {
        "time": "11 Nov 2020, 4:44:33 pm",
        "prod_name": "T-shirt",
        "action": "remove"
    },
    {
        "time": "11 Nov 2020, 4:44:34 pm",
        "prod_name": "Jacket",
        "action": "remove"
    },
    {
        "time": "11 Nov 2020, 4:58:25 pm",
        "prod_name": "Belt",
        "action": "add"
    },
    {
        "time": "11 Nov 2020, 4:58:25 pm",
        "prod_name": "T-shirt",
        "action": "add"
    },
    {
        "time": "11 Nov 2020, 4:58:26 pm",
        "prod_name": "Jacket",
        "action": "add"
    },
    {
        "time": "11 Nov 2020, 4:58:28 pm",
        "prod_name": "Belt",
        "action": "remove"
    },
    {
        "time": "11 Nov 2020, 4:58:29 pm",
        "prod_name": "T-shirt",
        "action": "remove"
    },
    {
        "time": "11 Nov 2020, 4:58:30 pm",
        "prod_name": "Jacket",
        "action": "remove"
    },
    {
        "time": "11 Nov 2020, 4:58:31 pm",
        "prod_name": "Belt",
        "action": "add"
    },
    {
        "time": "11 Nov 2020, 4:58:31 pm",
        "prod_name": "Belt",
        "action": "change"
    },
    {
        "time": "11 Nov 2020, 4:58:31 pm",
        "prod_name": "Belt",
        "action": "change"
    },
    {
        "time": "11 Nov 2020, 5:53:33 pm",
        "prod_name": "T-shirt",
        "action": "add"
    },
    {
        "time": "11 Nov 2020, 5:53:34 pm",
        "prod_name": "Belt",
        "action": "change"
    },
    {
        "time": "11 Nov 2020, 5:53:35 pm",
        "prod_name": "Jacket",
        "action": "add"
    },
    {
        "time": "11 Nov 2020, 6:42:47 pm",
        "prod_name": "Jacket",
        "action": "change"
    },
    {
        "time": "11 Nov 2020, 6:42:49 pm",
        "prod_name": "Belt",
        "action": "change"
    },
    {
        "time": "11 Nov 2020, 6:42:50 pm",
        "prod_name": "Belt",
        "action": "change"
    },
    {
        "time": "11 Nov 2020, 6:42:50 pm",
        "prod_name": "Belt",
        "action": "change"
    },
    {
        "time": "11 Nov 2020, 6:42:51 pm",
        "prod_name": "T-shirt",
        "action": "remove"
    },
    {
        "time": "11 Nov 2020, 6:42:52 pm",
        "prod_name": "Belt",
        "action": "remove"
    },
    {
        "time": "11 Nov 2020, 6:42:53 pm",
        "prod_name": "Jacket",
        "action": "change"
    },
    {
        "time": "11 Nov 2020, 6:47:47 pm",
        "prod_name": "Jacket",
        "action": "remove"
    },
    {
        "time": "11 Nov 2020, 6:54:46 pm",
        "prod_name": "Wamus",
        "action": "add"
    },
    {
        "time": "11 Nov 2020, 6:54:47 pm",
        "prod_name": "Costume",
        "action": "add"
    },
    {
        "time": "11 Nov 2020, 6:54:51 pm",
        "prod_name": "Wamus",
        "action": "remove"
    },
    {
        "time": "11 Nov 2020, 6:54:53 pm",
        "prod_name": "Costume",
        "action": "remove"
    },
    {
        "time": "11 Nov 2020, 7:23:01 pm",
        "prod_name": "Costume",
        "action": "add"
    },
    {
        "time": "11 Nov 2020, 7:23:02 pm",
        "prod_name": "Wamus",
        "action": "add"
    },
    {
        "time": "11 Nov 2020, 7:24:13 pm",
        "prod_name": "Costume",
        "action": "change"
    },
    {
        "time": "11 Nov 2020, 7:44:59 pm",
        "prod_name": "T-shirt",
        "action": "add"
    },
    {
        "time": "11 Nov 2020, 7:45:00 pm",
        "prod_name": "Jacket",
        "action": "add"
    },
    {
        "time": "11 Nov 2020, 7:45:01 pm",
        "prod_name": "Wamus",
        "action": "change"
    },
    {
        "time": "11 Nov 2020, 7:45:03 pm",
        "prod_name": "Costume",
        "action": "change"
    },
    {
        "time": "11 Nov 2020, 7:45:04 pm",
        "prod_name": "Costume",
        "action": "remove"
    },
    {
        "time": "11 Nov 2020, 7:45:04 pm",
        "prod_name": "Wamus",
        "action": "change"
    },
    {
        "time": "11 Nov 2020, 7:45:05 pm",
        "prod_name": "Wamus",
        "action": "remove"
    },
    {
        "time": "11 Nov 2020, 7:45:05 pm",
        "prod_name": "T-shirt",
        "action": "remove"
    },
    {
        "time": "11 Nov 2020, 7:45:05 pm",
        "prod_name": "Jacket",
        "action": "remove"
    },
    {
        "time": "11 Nov 2020, 7:49:07 pm",
        "prod_name": "Belt",
        "action": "add"
    },
    {
        "time": "11 Nov 2020, 7:49:08 pm",
        "prod_name": "T-shirt",
        "action": "add"
    },
    {
        "time": "11 Nov 2020, 7:49:09 pm",
        "prod_name": "Jacket",
        "action": "add"
    },
    {
        "time": "11 Nov 2020, 8:20:01 pm",
        "prod_name": "Jacket",
        "action": "remove"
    },
    {
        "time": "11 Nov 2020, 8:20:02 pm",
        "prod_name": "T-shirt",
        "action": "remove"
    },
    {
        "time": "11 Nov 2020, 8:20:03 pm",
        "prod_name": "Belt",
        "action": "remove"
    },
    {
        "time": "11 Nov 2020, 8:20:10 pm",
        "prod_name": "T-shirt",
        "action": "add"
    },
    {
        "time": "11 Nov 2020, 8:20:19 pm",
        "prod_name": "T-shirt",
        "action": "remove"
    },
    {
        "time": "11 Nov 2020, 8:34:12 pm",
        "prod_name": "Belt",
        "action": "add"
    },
    {
        "time": "11 Nov 2020, 8:34:15 pm",
        "prod_name": "Belt",
        "action": "remove"
    },
    {
        "time": "11 Nov 2020, 8:34:49 pm",
        "prod_name": "Belt",
        "action": "add"
    },
    {
        "time": "11 Nov 2020, 8:34:50 pm",
        "prod_name": "Pullover",
        "action": "add"
    },
    {
        "time": "11 Nov 2020, 8:34:51 pm",
        "prod_name": "T-shirt",
        "action": "add"
    },
    {
        "time": "12 Nov 2020, 10:21:02 am",
        "prod_name": "Belt",
        "action": "remove"
    },
    {
        "time": "12 Nov 2020, 10:21:02 am",
        "prod_name": "Pullover",
        "action": "remove"
    },
    {
        "time": "12 Nov 2020, 10:21:02 am",
        "prod_name": "T-shirt",
        "action": "remove"
    },
    {
        "time": "12 Nov 2020, 10:25:12 am",
        "prod_name": "T-shirt",
        "action": "add"
    },
    {
        "time": "12 Nov 2020, 10:25:12 am",
        "prod_name": "Jacket",
        "action": "add"
    },
    {
        "time": "12 Nov 2020, 10:45:02 am",
        "prod_name": "T-shirt",
        "action": "remove"
    },
    {
        "time": "12 Nov 2020, 10:45:03 am",
        "prod_name": "Jacket",
        "action": "remove"
    },
    {
        "time": "12 Nov 2020, 10:47:23 am",
        "prod_name": "T-shirt",
        "action": "add"
    },
    {
        "time": "12 Nov 2020, 10:47:24 am",
        "prod_name": "Belt",
        "action": "add"
    },
    {
        "time": "12 Nov 2020, 10:47:32 am",
        "prod_name": "Belt",
        "action": "remove"
    },
    {
        "time": "12 Nov 2020, 10:47:33 am",
        "prod_name": "T-shirt",
        "action": "remove"
    },
    {
        "time": "12 Nov 2020, 10:51:10 am",
        "prod_name": "Belt",
        "action": "add"
    },
    {
        "time": "12 Nov 2020, 10:51:10 am",
        "prod_name": "T-shirt",
        "action": "add"
    },
    {
        "time": "12 Nov 2020, 10:51:11 am",
        "prod_name": "Jacket",
        "action": "add"
    },
    {
        "time": "12 Nov 2020, 10:51:12 am",
        "prod_name": "Wamus",
        "action": "add"
    },
    {
        "time": "12 Nov 2020, 10:51:15 am",
        "prod_name": "Belt",
        "action": "remove"
    },
    {
        "time": "12 Nov 2020, 10:51:15 am",
        "prod_name": "T-shirt",
        "action": "remove"
    },
    {
        "time": "12 Nov 2020, 10:51:15 am",
        "prod_name": "Jacket",
        "action": "remove"
    },
    {
        "time": "12 Nov 2020, 10:51:16 am",
        "prod_name": "Wamus",
        "action": "remove"
    },
    {
        "time": "12 Nov 2020, 10:56:01 am",
        "prod_name": "Belt",
        "action": "add"
    },
    {
        "time": "12 Nov 2020, 11:01:13 am",
        "prod_name": "Belt",
        "action": "change"
    },
    {
        "time": "12 Nov 2020, 11:01:13 am",
        "prod_name": "T-shirt",
        "action": "add"
    },
    {
        "time": "12 Nov 2020, 11:01:14 am",
        "prod_name": "Jacket",
        "action": "add"
    },
    {
        "time": "12 Nov 2020, 11:01:15 am",
        "prod_name": "Costume",
        "action": "add"
    },
    {
        "time": "12 Nov 2020, 11:01:23 am",
        "prod_name": "Costume",
        "action": "remove"
    },
    {
        "time": "12 Nov 2020, 11:01:24 am",
        "prod_name": "Jacket",
        "action": "remove"
    },
    {
        "time": "12 Nov 2020, 11:01:25 am",
        "prod_name": "T-shirt",
        "action": "remove"
    },
    {
        "time": "12 Nov 2020, 11:01:26 am",
        "prod_name": "Belt",
        "action": "change"
    },
    {
        "time": "12 Nov 2020, 11:08:05 am",
        "prod_name": "Belt",
        "action": "remove"
    },
    {
        "time": "12 Nov 2020, 11:08:10 am",
        "prod_name": "Belt",
        "action": "add"
    },
    {
        "time": "12 Nov 2020, 11:08:11 am",
        "prod_name": "T-shirt",
        "action": "add"
    },
    {
        "time": "12 Nov 2020, 11:08:11 am",
        "prod_name": "Jacket",
        "action": "add"
    },
    {
        "time": "12 Nov 2020, 11:08:13 am",
        "prod_name": "Costume",
        "action": "add"
    },
    {
        "time": "12 Nov 2020, 11:08:13 am",
        "prod_name": "Tunic",
        "action": "add"
    },
    {
        "time": "12 Nov 2020, 11:08:16 am",
        "prod_name": "Belt",
        "action": "remove"
    },
    {
        "time": "12 Nov 2020, 11:08:17 am",
        "prod_name": "T-shirt",
        "action": "remove"
    },
    {
        "time": "12 Nov 2020, 11:08:17 am",
        "prod_name": "Jacket",
        "action": "remove"
    },
    {
        "time": "12 Nov 2020, 11:08:17 am",
        "prod_name": "Costume",
        "action": "remove"
    },
    {
        "time": "12 Nov 2020, 11:08:17 am",
        "prod_name": "Tunic",
        "action": "remove"
    },
    {
        "time": "12 Nov 2020, 11:11:56 am",
        "prod_name": "Belt",
        "action": "add"
    },
    {
        "time": "12 Nov 2020, 11:11:57 am",
        "prod_name": "Jacket",
        "action": "add"
    },
    {
        "time": "12 Nov 2020, 11:11:59 am",
        "prod_name": "Wamus",
        "action": "add"
    },
    {
        "time": "12 Nov 2020, 11:11:59 am",
        "prod_name": "Pullover",
        "action": "add"
    },
    {
        "time": "12 Nov 2020, 11:12:02 am",
        "prod_name": "Belt",
        "action": "remove"
    },
    {
        "time": "12 Nov 2020, 11:12:02 am",
        "prod_name": "Jacket",
        "action": "remove"
    },
    {
        "time": "12 Nov 2020, 11:12:02 am",
        "prod_name": "Wamus",
        "action": "remove"
    },
    {
        "time": "12 Nov 2020, 11:12:02 am",
        "prod_name": "Pullover",
        "action": "remove"
    },
    {
        "time": "12 Nov 2020, 11:12:06 am",
        "prod_name": "Belt",
        "action": "add"
    },
    {
        "time": "12 Nov 2020, 11:12:08 am",
        "prod_name": "T-shirt",
        "action": "add"
    },
    {
        "time": "12 Nov 2020, 11:12:09 am",
        "prod_name": "Jacket",
        "action": "add"
    },
    {
        "time": "12 Nov 2020, 11:24:05 am",
        "prod_name": "Belt",
        "action": "remove"
    },
    {
        "time": "12 Nov 2020, 11:24:05 am",
        "prod_name": "T-shirt",
        "action": "remove"
    },
    {
        "time": "12 Nov 2020, 11:24:06 am",
        "prod_name": "Jacket",
        "action": "remove"
    },
    {
        "time": "12 Nov 2020, 11:24:09 am",
        "prod_name": "Belt",
        "action": "add"
    },
    {
        "time": "12 Nov 2020, 11:24:10 am",
        "prod_name": "Jacket",
        "action": "add"
    },
    {
        "time": "12 Nov 2020, 11:24:11 am",
        "prod_name": "Wamus",
        "action": "add"
    },
    {
        "time": "12 Nov 2020, 11:35:15 am",
        "prod_name": "Wamus",
        "action": "change"
    },
    {
        "time": "12 Nov 2020, 11:35:16 am",
        "prod_name": "Belt",
        "action": "change"
    },
    {
        "time": "12 Nov 2020, 11:35:16 am",
        "prod_name": "T-shirt",
        "action": "add"
    },
    {
        "time": "12 Nov 2020, 11:49:49 am",
        "prod_name": "T-shirt",
        "action": "remove"
    },
    {
        "time": "12 Nov 2020, 11:49:50 am",
        "prod_name": "Jacket",
        "action": "remove"
    },
    {
        "time": "12 Nov 2020, 11:49:51 am",
        "prod_name": "Belt",
        "action": "change"
    },
    {
        "time": "12 Nov 2020, 11:49:53 am",
        "prod_name": "Belt",
        "action": "remove"
    },
    {
        "time": "12 Nov 2020, 11:49:54 am",
        "prod_name": "Wamus",
        "action": "change"
    },
    {
        "time": "12 Nov 2020, 11:49:55 am",
        "prod_name": "Wamus",
        "action": "remove"
    },
    {
        "time": "12 Nov 2020, 11:50:28 am",
        "prod_name": "Belt",
        "action": "add"
    },
    {
        "time": "12 Nov 2020, 11:50:28 am",
        "prod_name": "T-shirt",
        "action": "add"
    },
    {
        "time": "12 Nov 2020, 11:50:30 am",
        "prod_name": "Belt",
        "action": "remove"
    },
    {
        "time": "12 Nov 2020, 11:50:31 am",
        "prod_name": "T-shirt",
        "action": "remove"
    },
    {
        "time": "12 Nov 2020, 11:50:32 am",
        "prod_name": "Pullover",
        "action": "add"
    },
    {
        "time": "12 Nov 2020, 11:50:36 am",
        "prod_name": "Pullover",
        "action": "remove"
    },
    {
        "time": "12 Nov 2020, 11:51:17 am",
        "prod_name": "Pullover",
        "action": "add"
    },
    {
        "time": "12 Nov 2020, 11:51:17 am",
        "prod_name": "T-shirt",
        "action": "add"
    },
    {
        "time": "12 Nov 2020, 11:51:18 am",
        "prod_name": "Jacket",
        "action": "add"
    },
    {
        "time": "12 Nov 2020, 11:51:20 am",
        "prod_name": "Pullover",
        "action": "remove"
    },
    {
        "time": "12 Nov 2020, 11:51:24 am",
        "prod_name": "Tunic",
        "action": "add"
    },
    {
        "time": "12 Nov 2020, 11:51:27 am",
        "prod_name": "Costume",
        "action": "add"
    },
    {
        "time": "12 Nov 2020, 11:51:27 am",
        "prod_name": "Raincoat",
        "action": "add"
    },
    {
        "time": "12 Nov 2020, 11:51:30 am",
        "prod_name": "T-shirt",
        "action": "change"
    },
    {
        "time": "12 Nov 2020, 11:51:32 am",
        "prod_name": "Jacket",
        "action": "remove"
    },
    {
        "time": "12 Nov 2020, 11:51:32 am",
        "prod_name": "T-shirt",
        "action": "change"
    },
    {
        "time": "12 Nov 2020, 11:51:33 am",
        "prod_name": "Tunic",
        "action": "remove"
    },
    {
        "time": "12 Nov 2020, 11:52:40 am",
        "prod_name": "Costume",
        "action": "remove"
    },
    {
        "time": "12 Nov 2020, 11:52:46 am",
        "prod_name": "T-shirt",
        "action": "remove"
    },
    {
        "time": "12 Nov 2020, 11:52:47 am",
        "prod_name": "Raincoat",
        "action": "remove"
    },
    {
        "time": "12 Nov 2020, 11:55:39 am",
        "prod_name": "Pullover",
        "action": "add"
    },
    {
        "time": "12 Nov 2020, 11:55:39 am",
        "prod_name": "Belt",
        "action": "add"
    },
    {
        "time": "12 Nov 2020, 11:55:40 am",
        "prod_name": "T-shirt",
        "action": "add"
    },
    {
        "time": "12 Nov 2020, 11:55:42 am",
        "prod_name": "Pullover",
        "action": "remove"
    },
    {
        "time": "12 Nov 2020, 11:55:42 am",
        "prod_name": "Belt",
        "action": "remove"
    },
    {
        "time": "12 Nov 2020, 11:55:43 am",
        "prod_name": "T-shirt",
        "action": "remove"
    },
    {
        "time": "12 Nov 2020, 11:56:37 am",
        "prod_name": "Pullover",
        "action": "add"
    },
    {
        "time": "12 Nov 2020, 11:56:38 am",
        "prod_name": "Belt",
        "action": "add"
    },
    {
        "time": "12 Nov 2020, 11:56:38 am",
        "prod_name": "T-shirt",
        "action": "add"
    },
    {
        "time": "12 Nov 2020, 12:02:55 pm",
        "prod_name": "Pullover",
        "action": "remove"
    },
    {
        "time": "12 Nov 2020, 12:02:56 pm",
        "prod_name": "Belt",
        "action": "remove"
    },
    {
        "time": "12 Nov 2020, 12:02:57 pm",
        "prod_name": "T-shirt",
        "action": "remove"
    },
    {
        "time": "12 Nov 2020, 12:03:00 pm",
        "prod_name": "Pullover",
        "action": "add"
    },
    {
        "time": "12 Nov 2020, 12:03:01 pm",
        "prod_name": "Belt",
        "action": "add"
    },
    {
        "time": "12 Nov 2020, 12:03:01 pm",
        "prod_name": "T-shirt",
        "action": "add"
    },
    {
        "time": "12 Nov 2020, 12:03:06 pm",
        "prod_name": "Belt",
        "action": "remove"
    },
    {
        "time": "12 Nov 2020, 12:03:09 pm",
        "prod_name": "Pullover",
        "action": "remove"
    },
    {
        "time": "12 Nov 2020, 12:03:10 pm",
        "prod_name": "T-shirt",
        "action": "remove"
    },
    {
        "time": "12 Nov 2020, 12:04:41 pm",
        "prod_name": "Pullover",
        "action": "add"
    },
    {
        "time": "12 Nov 2020, 12:04:42 pm",
        "prod_name": "Belt",
        "action": "add"
    },
    {
        "time": "12 Nov 2020, 12:04:45 pm",
        "prod_name": "Belt",
        "action": "remove"
    },
    {
        "time": "12 Nov 2020, 12:04:46 pm",
        "prod_name": "Pullover",
        "action": "remove"
    },
    {
        "time": "12 Nov 2020, 12:08:05 pm",
        "prod_name": "Pullover",
        "action": "add"
    },
    {
        "time": "12 Nov 2020, 12:08:06 pm",
        "prod_name": "Belt",
        "action": "add"
    },
    {
        "time": "12 Nov 2020, 12:08:07 pm",
        "prod_name": "T-shirt",
        "action": "add"
    },
    {
        "time": "12 Nov 2020, 12:08:10 pm",
        "prod_name": "Pullover",
        "action": "remove"
    },
    {
        "time": "12 Nov 2020, 12:08:10 pm",
        "prod_name": "Belt",
        "action": "remove"
    },
    {
        "time": "12 Nov 2020, 12:08:11 pm",
        "prod_name": "T-shirt",
        "action": "remove"
    },
    {
        "time": "12 Nov 2020, 12:08:14 pm",
        "prod_name": "Wamus",
        "action": "add"
    },
    {
        "time": "12 Nov 2020, 12:08:16 pm",
        "prod_name": "Tunic",
        "action": "add"
    },
    {
        "time": "12 Nov 2020, 12:08:17 pm",
        "prod_name": "Costume",
        "action": "add"
    },
    {
        "time": "12 Nov 2020, 12:08:18 pm",
        "prod_name": "Raincoat",
        "action": "add"
    },
    {
        "time": "12 Nov 2020, 12:08:20 pm",
        "prod_name": "Costume",
        "action": "remove"
    },
    {
        "time": "12 Nov 2020, 12:08:21 pm",
        "prod_name": "Tunic",
        "action": "remove"
    },
    {
        "time": "12 Nov 2020, 12:08:21 pm",
        "prod_name": "Wamus",
        "action": "remove"
    },
    {
        "time": "12 Nov 2020, 12:08:22 pm",
        "prod_name": "Raincoat",
        "action": "remove"
    },
    {
        "time": "12 Nov 2020, 12:11:32 pm",
        "prod_name": "Pullover",
        "action": "add"
    },
    {
        "time": "12 Nov 2020, 12:11:32 pm",
        "prod_name": "Jacket",
        "action": "add"
    },
    {
        "time": "12 Nov 2020, 12:11:33 pm",
        "prod_name": "Tunic",
        "action": "add"
    },
    {
        "time": "12 Nov 2020, 12:11:39 pm",
        "prod_name": "Belt",
        "action": "add"
    },
    {
        "time": "12 Nov 2020, 12:12:23 pm",
        "prod_name": "Pullover",
        "action": "change"
    },
    {
        "time": "12 Nov 2020, 12:12:23 pm",
        "prod_name": "Belt",
        "action": "change"
    },
    {
        "time": "12 Nov 2020, 12:12:24 pm",
        "prod_name": "T-shirt",
        "action": "add"
    },
    {
        "time": "12 Nov 2020, 12:12:34 pm",
        "prod_name": "Pullover",
        "action": "change"
    },
    {
        "time": "12 Nov 2020, 12:12:35 pm",
        "prod_name": "Jacket",
        "action": "remove"
    },
    {
        "time": "12 Nov 2020, 12:12:35 pm",
        "prod_name": "Tunic",
        "action": "remove"
    },
    {
        "time": "12 Nov 2020, 12:12:35 pm",
        "prod_name": "Belt",
        "action": "change"
    },
    {
        "time": "12 Nov 2020, 12:12:36 pm",
        "prod_name": "Belt",
        "action": "remove"
    },
    {
        "time": "12 Nov 2020, 12:12:36 pm",
        "prod_name": "T-shirt",
        "action": "remove"
    },
    {
        "time": "12 Nov 2020, 12:12:40 pm",
        "prod_name": "Pullover",
        "action": "remove"
    },
    {
        "time": "12 Nov 2020, 12:12:45 pm",
        "prod_name": "Belt",
        "action": "add"
    },
    {
        "time": "12 Nov 2020, 12:12:46 pm",
        "prod_name": "T-shirt",
        "action": "add"
    },
    {
        "time": "12 Nov 2020, 12:12:46 pm",
        "prod_name": "Tunic",
        "action": "add"
    },
    {
        "time": "12 Nov 2020, 12:12:59 pm",
        "prod_name": "Wamus",
        "action": "add"
    },
    {
        "time": "12 Nov 2020, 12:13:00 pm",
        "prod_name": "Costume",
        "action": "add"
    },
    {
        "time": "12 Nov 2020, 12:13:01 pm",
        "prod_name": "Raincoat",
        "action": "add"
    },
    {
        "time": "12 Nov 2020, 12:13:04 pm",
        "prod_name": "Tunic",
        "action": "remove"
    },
    {
        "time": "12 Nov 2020, 12:13:04 pm",
        "prod_name": "Wamus",
        "action": "remove"
    },
    {
        "time": "12 Nov 2020, 12:13:04 pm",
        "prod_name": "Costume",
        "action": "remove"
    },
    {
        "time": "12 Nov 2020, 12:13:04 pm",
        "prod_name": "Raincoat",
        "action": "remove"
    },
    {
        "time": "12 Nov 2020, 12:13:06 pm",
        "prod_name": "Belt",
        "action": "remove"
    },
    {
        "time": "12 Nov 2020, 12:13:07 pm",
        "prod_name": "T-shirt",
        "action": "remove"
    }
]